{
  "color": {
    "palette": {
      "black": {
        "$type": "color",
        "$value": "#1a1a1a"
      },
      "white": {
        "$type": "color",
        "$value": "#ffffff"
      },
      "mono": {
        "50": {
          "$type": "color",
          "$value": "#f7f8f8"
        },
        "100": {
          "$type": "color",
          "$value": "#eef0f0"
        },
        "200": {
          "$type": "color",
          "$value": "#d9dede"
        },
        "300": {
          "$type": "color",
          "$value": "#c2cbca"
        },
        "400": {
          "$type": "color",
          "$value": "#90a09e"
        },
        "500": {
          "$type": "color",
          "$value": "#728583"
        },
        "600": {
          "$type": "color",
          "$value": "#5c6d6c"
        },
        "700": {
          "$type": "color",
          "$value": "#4b5958"
        },
        "800": {
          "$type": "color",
          "$value": "#414b4a"
        },
        "900": {
          "$type": "color",
          "$value": "#394141"
        },
        "950": {
          "$type": "color",
          "$value": "#262b2b"
        }
      },
      "negative": {
        "50": {
          "$type": "color",
          "$value": "#fcf4f4"
        },
        "100": {
          "$type": "color",
          "$value": "#fae6e6"
        },
        "200": {
          "$type": "color",
          "$value": "#f6d2d2"
        },
        "300": {
          "$type": "color",
          "$value": "#eca2a2"
        },
        "400": {
          "$type": "color",
          "$value": "#e48585"
        },
        "500": {
          "$type": "color",
          "$value": "#d65d5d"
        },
        "600": {
          "$type": "color",
          "$value": "#c14141"
        },
        "700": {
          "$type": "color",
          "$value": "#a23333"
        },
        "800": {
          "$type": "color",
          "$value": "#862e2e"
        },
        "900": {
          "$type": "color",
          "$value": "#712b2b"
        },
        "950": {
          "$type": "color",
          "$value": "#3c1313"
        }
      },
      "warning": {
        "50": {
          "$type": "color",
          "$value": "#fafaec"
        },
        "100": {
          "$type": "color",
          "$value": "#f4f4cd"
        },
        "200": {
          "$type": "color",
          "$value": "#ece8a2"
        },
        "300": {
          "$type": "color",
          "$value": "#dfd465"
        },
        "400": {
          "$type": "color",
          "$value": "#d4c03b"
        },
        "500": {
          "$type": "color",
          "$value": "#c5aa2d"
        },
        "600": {
          "$type": "color",
          "$value": "#aa8824"
        },
        "700": {
          "$type": "color",
          "$value": "#886420"
        },
        "800": {
          "$type": "color",
          "$value": "#715122"
        },
        "900": {
          "$type": "color",
          "$value": "#614422"
        },
        "950": {
          "$type": "color",
          "$value": "#382410"
        }
      },
      "positive": {
        "50": {
          "$type": "color",
          "$value": "#f1fcf3"
        },
        "100": {
          "$type": "color",
          "$value": "#defae4"
        },
        "200": {
          "$type": "color",
          "$value": "#bff3ca"
        },
        "300": {
          "$type": "color",
          "$value": "#a2ecb3"
        },
        "400": {
          "$type": "color",
          "$value": "#54d472"
        },
        "500": {
          "$type": "color",
          "$value": "#2dba4e"
        },
        "600": {
          "$type": "color",
          "$value": "#20993d"
        },
        "700": {
          "$type": "color",
          "$value": "#1c7933"
        },
        "800": {
          "$type": "color",
          "$value": "#1b602c"
        },
        "900": {
          "$type": "color",
          "$value": "#184f27"
        },
        "950": {
          "$type": "color",
          "$value": "#082b11"
        }
      },
      "accent": {
        "50": {
          "$type": "color",
          "$value": "#f1fcf9"
        },
        "100": {
          "$type": "color",
          "$value": "#d1f6ed"
        },
        "200": {
          "$type": "color",
          "$value": "#a2ecdb"
        },
        "300": {
          "$type": "color",
          "$value": "#6ddbc6"
        },
        "400": {
          "$type": "color",
          "$value": "#3fc2ad"
        },
        "500": {
          "$type": "color",
          "$value": "#25a793"
        },
        "600": {
          "$type": "color",
          "$value": "#1b8678"
        },
        "700": {
          "$type": "color",
          "$value": "#1a6b62"
        },
        "800": {
          "$type": "color",
          "$value": "#195650"
        },
        "900": {
          "$type": "color",
          "$value": "#194843"
        },
        "950": {
          "$type": "color",
          "$value": "#092a29"
        }
      }
    }
  }
}